snusbase/__init__.py
snusbase/__main__.py
snusbase.py-1.0.7.dist-info/LICENSE
snusbase.py-1.0.7.dist-info/METADATA
snusbase.py-1.0.7.dist-info/WHEEL
snusbase.py-1.0.7.dist-info/top_level.txt
snusbase.py-1.0.7.dist-info/RECORD
