Metadata-Version: 2.1
Name: snusbase.py
Version: 1.0.7
Summary: an unofficial async wrapper for the Snusbase API
Author-email: igna <igna@incel.email>
License: MIT License
Project-URL: Homepage, https://snusbase.com
Project-URL: Bug Reports, https://github.com/8841fb/snusbase.py/issues
Project-URL: Source, https://github.com/8841fb/snusbase.py
Keywords: snusbase,osint
Classifier: Development Status :: 5 - Production/Stable
Classifier: Intended Audience :: Developers
Classifier: Topic :: Software Development :: Libraries
Classifier: License :: OSI Approved :: MIT License
Classifier: Programming Language :: Python :: 3
Classifier: Programming Language :: Python :: 3.7
Classifier: Programming Language :: Python :: 3.8
Classifier: Programming Language :: Python :: 3.9
Classifier: Programming Language :: Python :: 3.10
Classifier: Programming Language :: Python :: 3.11
Classifier: Programming Language :: Python :: 3.12
Classifier: Programming Language :: Python :: 3 :: Only
Requires-Python: >=3.7
License-File: LICENSE
Requires-Dist: httpx >=0.26.0
Provides-Extra: dev
Requires-Dist: check-manifest ; extra == 'dev'
Provides-Extra: test
Requires-Dist: coverage ; extra == 'test'
